perceptron/__init__.py
perceptron/NeuralNetwork/NeuralNetwork.py
perceptron/NeuralNetwork/__init__.py
perceptron/Neuron/Neuron.py
perceptron/Neuron/__init__.py
perceptron/Neuron/functions.py
sweet_perceptron-1.0.1.dist-info/LICENSE
sweet_perceptron-1.0.1.dist-info/METADATA
sweet_perceptron-1.0.1.dist-info/WHEEL
sweet_perceptron-1.0.1.dist-info/top_level.txt
sweet_perceptron-1.0.1.dist-info/RECORD
