Metadata-Version: 2.1
Name: sweet-perceptron
Version: 1.0.1
Summary: A simple neural network library
Home-page: https://github.com/SweetBubaleXXX/sweet-perceptron
Author: SweetBubaleXXX
Author-email: 1pcpcpc1pc@gmail.com
License: MIT
Project-URL: Bug Tracker, https://github.com/SweetBubaleXXX/sweet-perceptron/issues
Platform: UNKNOWN
Classifier: Programming Language :: Python :: 3
Classifier: License :: OSI Approved :: MIT License
Classifier: Operating System :: OS Independent
Requires-Python: >=3.8
License-File: LICENSE
Requires-Dist: numpy (>=1.15.0)
